{"_id":{"$oid":"658c638118dd9a4364fe6be5"},"datetime":"10/10/1986 20:00","city":"holmes/pawling","state":"ny","country":"NULL","shape":"chevron","duration_seconds":180,"duration_hours_min":"3 minutes","comments":"Football Field Sized Chevron with bright white lights on front&#44 moving slowly with absolutely no sound","date posted":"08/10/2007","latitude":41.523427,"longitude":-73.646795}
{"_id":{"$oid":"658c638118dd9a4364fe6c55"},"datetime":"10/10/2004 15:00","city":"rock island","state":"il","country":"us","shape":"sphere","duration_seconds":3600,"duration_hours_min":"1 hour","comments":"The sky was clear  and the objects at times appeared to rotate slowly.","date posted":"27/10/2004","latitude":41.5094444,"longitude":-90.5786111}
{"_id":{"$oid":"658c638118dd9a4364fe6c57"},"datetime":"10/10/2006 23:00","city":"lyndhurst","state":"oh","country":"us","shape":"unknown","duration_seconds":300,"duration_hours_min":"5 minutes","comments":"This is a follow up to my Feb. 16th&#44 1995 report.  This past Tuesday&#44 my wife and I AGAIN heard the same loud&#44 rumbling roar that we he","date posted":"30/10/2006","latitude":41.52,"longitude":-81.4888889}
{"_id":{"$oid":"658c638118dd9a4364fe6c9d"},"datetime":"10/10/2011 14:30","city":"north kingstown","state":"ri","country":"us","shape":"oval","duration_seconds":40,"duration_hours_min":"40 sec","comments":"Bright oval object in sky","date posted":"25/10/2011","latitude":41.55,"longitude":-71.4666667}
{"_id":{"$oid":"658c638118dd9a4364fe6ca6"},"datetime":"10/10/2011 21:00","city":"lakewood","state":"oh","country":"us","shape":"fireball","duration_seconds":60,"duration_hours_min":"1 minute","comments":"Orange light flies overhead and turns black as it passed silently.","date posted":"12/12/2011","latitude":41.4819444,"longitude":-81.7983333}
{"_id":{"$oid":"658c638118dd9a4364fe6d07"},"datetime":"11/10/2003 13:00","city":"nebraska (above?&#44 or above south dakota)","state":"ne","country":"NULL","shape":"cigar","duration_seconds":2,"duration_hours_min":"seconds","comments":"rather large cigar shaped object photographed from airplane window","date posted":"15/10/2003","latitude":41.492537,"longitude":-99.901813}
{"_id":{"$oid":"658c638118dd9a4364fe6d9b"},"datetime":"01/10/1965 21:00","city":"dushore","state":"pa","country":"us","shape":"disk","duration_seconds":300,"duration_hours_min":"5 minutes","comments":"It could move very slowly or very quickly but either way it moved without making any noise.","date posted":"16/04/2005","latitude":41.5241667,"longitude":-76.4011111}
{"_id":{"$oid":"658c638118dd9a4364fe6db6"},"datetime":"01/10/1970 19:00","city":"summit lake indian reservation","state":"nv","country":"NULL","shape":"oval","duration_seconds":1500,"duration_hours_min":"25min.","comments":"ball of light&#44 turned into a doughnut shape&#44 assention&#44 stream&#44 4 witnesses&#44seen from higher elevation.","date posted":"11/08/2004","latitude":41.524898,"longitude":-119.05102}
{"_id":{"$oid":"658c638118dd9a4364fe6e9b"},"datetime":"01/10/2005 00:00","city":"evergreen park/tinley park/orland park","state":"il","country":"NULL","shape":"light","duration_seconds":9000,"duration_hours_min":"from 11pm - 1:30 am","comments":"strange. dozens saw it . happens all the time","date posted":"11/10/2005","latitude":41.462072,"longitude":-87.894245}
{"_id":{"$oid":"658c638118dd9a4364fe6eae"},"datetime":"01/10/2005 01:10","city":"manhattan","state":"il","country":"us","shape":"triangle","duration_seconds":10,"duration_hours_min":"10 seconds","comments":"Tinley Park Lights Are Back&#33&#33&#33","date posted":"11/10/2005","latitude":41.4225,"longitude":-87.9858333}
{"_id":{"$oid":"658c638118dd9a4364fe6f18"},"datetime":"01/10/2008 01:00","city":"bryan","state":"oh","country":"us","shape":"cylinder","duration_seconds":120,"duration_hours_min":"2 minuites","comments":"It was cylinder shaped and had lights all around it. 500 Lights On Object0: Yes","date posted":"31/10/2008","latitude":41.4747222,"longitude":-84.5525}
{"_id":{"$oid":"658c638218dd9a4364fe7044"},"datetime":"12/10/2012 19:10","city":"hadlyme","state":"ct","country":"us","shape":"light","duration_seconds":300,"duration_hours_min":"5 minutes","comments":"Bright ascending light&#44 vanished in a flash","date posted":"30/10/2012","latitude":41.4202778,"longitude":-72.4069444}
{"_id":{"$oid":"658c638218dd9a4364fe7123"},"datetime":"13/10/2010 22:45","city":"etna","state":"ca","country":"us","shape":"flash","duration_seconds":1500,"duration_hours_min":"25 minutes","comments":"UFO Rotating Red Green Yellow Lights","date posted":"21/11/2010","latitude":41.4569444,"longitude":-122.8936111}
{"_id":{"$oid":"658c638218dd9a4364fe71c7"},"datetime":"14/10/2002 22:15","city":"clarks summit","state":"pa","country":"us","shape":"circle","duration_seconds":10,"duration_hours_min":"10 seconds","comments":"I was driving on Interstate 81 when my 10 y.o. son said&quot;mom what kind of plane is that? I look up and saw an object that looked like a","date posted":"28/10/2002","latitude":41.4886111,"longitude":-75.7088889}
{"_id":{"$oid":"658c638218dd9a4364fe71f8"},"datetime":"14/10/2008 01:30","city":"valparaiso","state":"in","country":"us","shape":"formation","duration_seconds":5,"duration_hours_min":"5 seconds","comments":"Three brownish-orange craft","date posted":"31/10/2008","latitude":41.4730556,"longitude":-87.0611111}
{"_id":{"$oid":"658c638218dd9a4364fe72cd"},"datetime":"15/10/1982 22:00","city":"narragansette","state":"ri","country":"NULL","shape":"chevron","duration_seconds":15,"duration_hours_min":"15 seconds","comments":"boomerang shaped object with 5 greenish lights growing in size and then turned and disappeared","date posted":"19/03/2009","latitude":41.450084,"longitude":-71.449503}
{"_id":{"$oid":"658c638218dd9a4364fe72db"},"datetime":"15/10/1985 07:00","city":"cleveland (massilon rd.&#44  montrose area)","state":"oh","country":"us","shape":"diamond","duration_seconds":15,"duration_hours_min":"15 seconds","comments":"Driving on rural road AM. Cant rember month but there was no leaves on trees.  I saw a &quot;kite shaped object&quot; about the size of a two sto","date posted":"19/09/2002","latitude":41.4994444,"longitude":-81.6955556}
{"_id":{"$oid":"658c638218dd9a4364fe733a"},"datetime":"15/10/1997 03:00","city":"brigham city (west of)","state":"ut","country":"us","shape":"other","duration_seconds":180,"duration_hours_min":"3 min","comments":"VERY LARGE GLOWING OBJECT HOVERED TO THE WEST OF THE SALT LAKE DISAPERING AFTER ABOUT 3 MIN","date posted":"06/09/2002","latitude":41.5102778,"longitude":-112.0147222}
{"_id":{"$oid":"658c638218dd9a4364fe735c"},"datetime":"15/10/1998 21:15","city":"westlake","state":"oh","country":"us","shape":"light","duration_seconds":60,"duration_hours_min":"60 seconds","comments":"Witnessed flyby by a craft composed of six perfectly round&#44 bright lights.","date posted":"28/01/1999","latitude":41.4552778,"longitude":-81.9180556}
{"_id":{"$oid":"658c638218dd9a4364fe73ff"},"datetime":"15/10/2005 11:00","city":"joliet","state":"il","country":"us","shape":"flash","duration_seconds":1,"duration_hours_min":"half second","comments":"A large flash in the sky&#44 only for a short time.","date posted":"11/03/2006","latitude":41.525,"longitude":-88.0816667}
{"_id":{"$oid":"658c638218dd9a4364fe746c"},"datetime":"15/10/2011 20:05","city":"muscatine","state":"ia","country":"us","shape":"triangle","duration_seconds":120,"duration_hours_min":"a few minutes","comments":"Three bright lights in the sky in the shape of a triangle","date posted":"19/10/2011","latitude":41.4244444,"longitude":-91.0430556}
{"_id":{"$oid":"658c638218dd9a4364fe7509"},"datetime":"16/10/2008 19:35","city":"avon","state":"oh","country":"us","shape":"oval","duration_seconds":300,"duration_hours_min":"5 minutes","comments":"Oblong UFO with red/white lights (Elyria&#44 OH)","date posted":"31/10/2008","latitude":41.4516667,"longitude":-82.0355556}
{"_id":{"$oid":"658c638218dd9a4364fe7533"},"datetime":"16/10/2011 19:45","city":"matteson","state":"il","country":"us","shape":"circle","duration_seconds":900,"duration_hours_min":"15 mins","comments":"A bright blue light all around it and a red light under it.&#44 it was not moving for about 10mins after that started moving very slow","date posted":"25/10/2011","latitude":41.5038889,"longitude":-87.7130556}
{"_id":{"$oid":"658c638218dd9a4364fe75fb"},"datetime":"17/10/2011 19:45","city":"new lenox","state":"il","country":"us","shape":"disk","duration_seconds":180,"duration_hours_min":"3 minutes","comments":"Two witnesses watch 30ft disc fall from high altitude in seconds&#44 change axis&#44 stop 30ft over highway&#44 pass slowly and silently between","date posted":"20/06/2012","latitude":41.5119444,"longitude":-87.9655556}
{"_id":{"$oid":"658c638218dd9a4364fe7631"},"datetime":"18/10/1989 13:00","city":"wallingford","state":"ct","country":"us","shape":"oval","duration_seconds":1200,"duration_hours_min":"20 mins.","comments":"The craft was pure white. It made no noise. The sea gulls did not sense it. It was going about 200 mph. It was at about 1000 ft. It tra","date posted":"22/02/2005","latitude":41.4569444,"longitude":-72.8236111}
{"_id":{"$oid":"658c638218dd9a4364fe763f"},"datetime":"18/10/1998 04:30","city":"bettendorf","state":"ia","country":"us","shape":"sphere","duration_seconds":420,"duration_hours_min":"5-7 min.","comments":"SOFT BALL SIZE FLOATING BALL OF LIGHT.  APPEARED TO BE UNDER SOME TYPE OF CONTROL.","date posted":"01/11/1998","latitude":41.5244444,"longitude":-90.5155556}
{"_id":{"$oid":"658c638218dd9a4364fe7699"},"datetime":"18/10/2008 08:05","city":"cornwall","state":"ny","country":"NULL","shape":"disk","duration_seconds":5,"duration_hours_min":"5 seconds","comments":"Disc shaped object stationary above neighborhood","date posted":"31/10/2008","latitude":41.434338,"longitude":-74.035368}
{"_id":{"$oid":"658c638218dd9a4364fe76ca"},"datetime":"18/10/2012 20:50","city":"bay village","state":"oh","country":"us","shape":"sphere","duration_seconds":600,"duration_hours_min":"10 minutes","comments":"While taking an evening walk&#44 I noticed a pair of two orange objects flying NNW in the sky below the cloud cover.","date posted":"30/10/2012","latitude":41.4847222,"longitude":-81.9222222}
{"_id":{"$oid":"658c638218dd9a4364fe77d4"},"datetime":"20/10/1985 05:00","city":"throop","state":"pa","country":"us","shape":"oval","duration_seconds":14400,"duration_hours_min":"hours","comments":"5 nights of peculiar light with mini lights going to and fro.","date posted":"23/12/2002","latitude":41.4513889,"longitude":-75.6122222}
{"_id":{"$oid":"658c638218dd9a4364fe77d5"},"datetime":"20/10/1976 00:00","city":"avon lake","state":"oh","country":"us","shape":"circle","duration_seconds":900,"duration_hours_min":"10 to 15 minutes","comments":"The object emitted a brilliant white light&#44 two smaller objects separated from the main object&#44 we ran into the house&#44 the object must","date posted":"16/07/2006","latitude":41.5052778,"longitude":-82.0283333}
{"_id":{"$oid":"658c638218dd9a4364fe785c"},"datetime":"20/10/2005 22:30","city":"moline","state":"il","country":"us","shape":"triangle","duration_seconds":120,"duration_hours_min":"2 minutes","comments":"A huge giant black isoceles triangular craft flew over in total silence and then took off at Mach 10","date posted":"12/05/2009","latitude":41.5066667,"longitude":-90.515}
{"_id":{"$oid":"658c638218dd9a4364fe78bb"},"datetime":"20/10/2011 21:15","city":"muscatine","state":"ia","country":"us","shape":"light","duration_seconds":180,"duration_hours_min":"3 min.","comments":"five bright yellow lights leading huge craft","date posted":"25/10/2011","latitude":41.4244444,"longitude":-91.0430556}
{"_id":{"$oid":"658c638218dd9a4364fe78f9"},"datetime":"21/10/1988 21:00","city":"holmes/pawling","state":"ny","country":"NULL","shape":"formation","duration_seconds":1200,"duration_hours_min":"20 min aprox","comments":"Flyimg V seen over whaley lake/pawling.no ultra lites this time","date posted":"28/05/2005","latitude":41.523427,"longitude":-73.646795}
{"_id":{"$oid":"658c638218dd9a4364fe7938"},"datetime":"21/10/2006 00:00","city":"north kingstown","state":"ri","country":"us","shape":"circle","duration_seconds":4,"duration_hours_min":"4 seconds","comments":"Flew 50 feet in air&#44 one after another&#44 came back towards us&#44 and then went back into the opposite direction.","date posted":"01/02/2007","latitude":41.55,"longitude":-71.4666667}
{"_id":{"$oid":"658c638218dd9a4364fe79a0"},"datetime":"21/10/2012 23:30","city":"cleveland","state":"oh","country":"us","shape":"disk","duration_seconds":120,"duration_hours_min":"~2 minutes","comments":"As I was driving my friend home we both saw what appeared to be an airplane on I-90 East towards Cleveland.","date posted":"30/10/2012","latitude":41.4994444,"longitude":-81.6955556}
{"_id":{"$oid":"658c638218dd9a4364fe79b9"},"datetime":"02/10/1988 22:30","city":"fishkill","state":"ny","country":"us","shape":"formation","duration_seconds":600,"duration_hours_min":"10 minutes","comments":"Lights over Fishkill N.Y.","date posted":"12/10/2001","latitude":41.5355556,"longitude":-73.8994444}
{"_id":{"$oid":"658c638218dd9a4364fe79c4"},"datetime":"02/10/1998 19:55","city":"bettendorf","state":"ia","country":"us","shape":"light","duration_seconds":60,"duration_hours_min":"1 minute","comments":"Heavy Blue Light beamed down and chased family in house&#44 simular to 50 foot wide search light.","date posted":"01/11/1998","latitude":41.5244444,"longitude":-90.5155556}
{"_id":{"$oid":"658c638218dd9a4364fe7a1d"},"datetime":"02/10/2008 19:52","city":"middletown","state":"ny","country":"us","shape":"light","duration_seconds":3600,"duration_hours_min":"1hr +","comments":"Large bright light with aircraft below it shows to me that it is not an aircraft.","date posted":"31/10/2008","latitude":41.4458333,"longitude":-74.4233333}
{"_id":{"$oid":"658c638218dd9a4364fe7a57"},"datetime":"02/10/2013 19:50","city":"meriden","state":"ct","country":"us","shape":"disk","duration_seconds":15,"duration_hours_min":"15 seconds","comments":"Bright blue disk with two bright red lights&#44 hovering and moving back and forth in the sky until it disappeared.","date posted":"03/10/2013","latitude":41.5380556,"longitude":-72.8075}
{"_id":{"$oid":"658c638218dd9a4364fe7b04"},"datetime":"22/10/2011 20:45","city":"crown point","state":"in","country":"us","shape":"circle","duration_seconds":300,"duration_hours_min":"3 - 5 min.","comments":"Red glowing circular object moving laterally South to North with no sound (about the size of an aircraft)","date posted":"25/10/2011","latitude":41.4169444,"longitude":-87.3652778}
{"_id":{"$oid":"658c638218dd9a4364fe7b52"},"datetime":"23/10/2000 06:50","city":"southbury","state":"ct","country":"us","shape":"light","duration_seconds":180,"duration_hours_min":"3 minutes","comments":"A very clear object that was covered with lights&#44 hovering in the air to create a triangle with two planets&#44 its lower lights blinked.","date posted":"02/12/2000","latitude":41.4813889,"longitude":-73.2136111}
{"_id":{"$oid":"658c638218dd9a4364fe7b61"},"datetime":"23/10/2003 10:15","city":"south kingstown","state":"ri","country":"NULL","shape":"unknown","duration_seconds":2,"duration_hours_min":"2 seconds","comments":"Loud explosion heard along southern Rhode Island coast.","date posted":"31/10/2003","latitude":41.447569,"longitude":-71.524667}
{"_id":{"$oid":"658c638218dd9a4364fe7c0e"},"datetime":"23/10/2013 19:45","city":"cedarville","state":"ca","country":"us","shape":"light","duration_seconds":1200,"duration_hours_min":"20 minutes","comments":"Bright glowing&#44spherical&#44 balls of light that dart around the sky with silence an super speed an gracefulness.","date posted":"11/11/2013","latitude":41.5291667,"longitude":-120.1722222}
{"_id":{"$oid":"658c638218dd9a4364fe7c7e"},"datetime":"24/10/2007 17:25","city":"columbus","state":"ne","country":"us","shape":"sphere","duration_seconds":600,"duration_hours_min":"5-10 min","comments":"4 to 5  shinny object with no sound flew over the house heading due west.","date posted":"28/11/2007","latitude":41.4297222,"longitude":-97.3680556}
{"_id":{"$oid":"658c638218dd9a4364fe7ce4"},"datetime":"24/10/2013 19:15","city":"cedarville","state":"ca","country":"us","shape":"light","duration_seconds":3600,"duration_hours_min":"45-60 minutes","comments":"Small red light followed by orange orbs that appeared&#44 multiplied&#44 and disappeared.","date posted":"11/11/2013","latitude":41.5291667,"longitude":-120.1722222}
{"_id":{"$oid":"658c638218dd9a4364fe7d00"},"datetime":"25/10/1975 22:25","city":"muscatine (area approx. 7mi south)","state":"ia","country":"us","shape":"circle","duration_seconds":12,"duration_hours_min":"10 to 12 sec","comments":"A formation of approx. 16 round fire orange guided craft entered the western sky at &quot;10 o&#39clock&quot; attitude. As I was watching the clear","date posted":"02/04/1999","latitude":41.4244444,"longitude":-91.0430556}
{"_id":{"$oid":"658c638218dd9a4364fe7d1b"},"datetime":"25/10/1999 12:18","city":"corinne","state":"ut","country":"us","shape":"disk","duration_seconds":15,"duration_hours_min":"15 seconds","comments":"A bright white disk-shaped object flew in veiw.","date posted":"02/11/1999","latitude":41.5511111,"longitude":-112.1094444}
{"_id":{"$oid":"658c638218dd9a4364fe7d76"},"datetime":"25/10/2008 23:00","city":"doris/weed (between)","state":"ca","country":"NULL","shape":"sphere","duration_seconds":2,"duration_hours_min":"a few seconds","comments":"Bright sphere shooting down the sky.","date posted":"31/10/2008","latitude":41.42265,"longitude":-122.386127}
{"_id":{"$oid":"658c638218dd9a4364fe7d98"},"datetime":"25/10/2011 18:20","city":"matteson","state":"il","country":"us","shape":"triangle","duration_seconds":1200,"duration_hours_min":"15-20 min","comments":"Triangle Formation of Bright lights in SKY","date posted":"12/12/2011","latitude":41.5038889,"longitude":-87.7130556}
{"_id":{"$oid":"658c638218dd9a4364fe7d99"},"datetime":"25/10/2011 18:20","city":"matteson","state":"il","country":"us","shape":"formation","duration_seconds":1200,"duration_hours_min":"20min","comments":"Triangle formation of 3 Bright White Lights in Sky over matteson IL","date posted":"12/12/2011","latitude":41.5038889,"longitude":-87.7130556}
{"_id":{"$oid":"658c638218dd9a4364fe7e60"},"datetime":"26/10/2012 10:01","city":"cheshire","state":"ct","country":"us","shape":"other","duration_seconds":19,"duration_hours_min":"~19 seconds","comments":"Small UFO over garden&#44 daylight&#44 120 feet away&#44 19 second vid&#44 Cheshire&#44 CT&#44 Oct 2012","date posted":"02/05/2014","latitude":41.4988889,"longitude":-72.9011111}
{"_id":{"$oid":"658c638218dd9a4364fe7f08"},"datetime":"27/10/2012 14:15","city":"valparaiso","state":"in","country":"us","shape":"chevron","duration_seconds":240,"duration_hours_min":"4 minutes","comments":"Black chevron shaped aircraft.","date posted":"30/10/2012","latitude":41.4730556,"longitude":-87.0611111}
{"_id":{"$oid":"658c638218dd9a4364fe7f21"},"datetime":"27/10/2013 19:30","city":"lorain","state":"oh","country":"us","shape":"diamond","duration_seconds":120,"duration_hours_min":"2 minutes","comments":"8 crafts or whatever&#44 proceeding W to E along Lake Erie shore line&#44 red&#44 silent&#44 with varying speeds&#44 but generally in formation.","date posted":"11/11/2013","latitude":41.4527778,"longitude":-82.1825}
{"_id":{"$oid":"658c638218dd9a4364fe7f48"},"datetime":"28/10/2000 20:30","city":"scranton","state":"pa","country":"us","shape":"other","duration_seconds":180,"duration_hours_min":"3 mins","comments":"It appeared to be a plane hovering in one spot with inverted wings and strange bubble-shaped objects underneath its wings.","date posted":"21/03/2003","latitude":41.4088889,"longitude":-75.6627778}
{"_id":{"$oid":"658c638218dd9a4364fe7f52"},"datetime":"28/10/2001 01:20","city":"carlisle","state":"ia","country":"us","shape":"chevron","duration_seconds":5,"duration_hours_min":"5 seconds","comments":"Green Chevron Shaped Craft Drops from Sky and Disappears","date posted":"20/11/2001","latitude":41.5008333,"longitude":-93.4908333}
{"_id":{"$oid":"658c638218dd9a4364fe7f62"},"datetime":"28/10/2002 19:30","city":"syracuse","state":"in","country":"us","shape":"light","duration_seconds":30,"duration_hours_min":"couple hours","comments":"something wierd happened","date posted":"04/11/2002","latitude":41.4277778,"longitude":-85.7525}
{"_id":{"$oid":"658c638218dd9a4364fe7f63"},"datetime":"28/10/2002 22:30","city":"syracuse","state":"in","country":"us","shape":"oval","duration_seconds":7200,"duration_hours_min":"2 hours stillgoing","comments":"oval dull lights - first there were two&#44 one was flying right behind the other and flying in a circle then the back one caught up to th","date posted":"04/11/2002","latitude":41.4277778,"longitude":-85.7525}
{"_id":{"$oid":"658c638218dd9a4364fe7f81"},"datetime":"28/10/2005 14:00","city":"kendallville","state":"in","country":"us","shape":"sphere","duration_seconds":15,"duration_hours_min":"15 sec. or less","comments":"On friday Oct. 28&#44 2005&#44 a co-worker and I (of 7 years) were sitting outside our plant near the loading dock around 2:00pm. Our company","date posted":"08/11/2005","latitude":41.4413889,"longitude":-85.265}
{"_id":{"$oid":"658c638218dd9a4364fe7fe8"},"datetime":"28/10/2011 21:30","city":"jermyn","state":"pa","country":"us","shape":"other","duration_seconds":240,"duration_hours_min":"4 mins","comments":"Jet tailing a completely blacked out silent object","date posted":"12/12/2011","latitude":41.5308333,"longitude":-75.5458333}
{"_id":{"$oid":"658c638218dd9a4364fe8033"},"datetime":"29/10/2001 22:30","city":"shorewood","state":"il","country":"us","shape":"disk","duration_seconds":30,"duration_hours_min":"30 seconds","comments":"Very large disk with a blue light on the bottom and 2 or more red lights on the sides. Made no noise whatsoever.","date posted":"11/08/2004","latitude":41.52,"longitude":-88.2016667}
{"_id":{"$oid":"658c638218dd9a4364fe805f"},"datetime":"29/10/2006 18:00","city":"crest hill","state":"il","country":"us","shape":"disk","duration_seconds":240,"duration_hours_min":"4 minutes","comments":"I witnessed 2 (UFO&#39s?) approximately 6:45 p.m. Sunday evening&#44 10/29/06 travelling west to east&#44 and the same height and speed as a com","date posted":"07/12/2006","latitude":41.5547222,"longitude":-88.0986111}
{"_id":{"$oid":"658c638218dd9a4364fe807e"},"datetime":"29/10/2008 20:00","city":"jermyn","state":"pa","country":"us","shape":"light","duration_seconds":300,"duration_hours_min":"5 minutes","comments":"Two aircraft circling light&#44 light disappears&#44 streaks between them later.","date posted":"31/10/2008","latitude":41.5308333,"longitude":-75.5458333}
{"_id":{"$oid":"658c638218dd9a4364fe81a6"},"datetime":"30/10/2013 19:00","city":"scranton","state":"pa","country":"us","shape":"light","duration_seconds":3600,"duration_hours_min":"1 hour","comments":"Extremely bright ball of light over West Scranton.  ((NUFORC Note:  Possible sighting of Venus?  PD))","date posted":"11/11/2013","latitude":41.4088889,"longitude":-75.6627778}
{"_id":{"$oid":"658c638218dd9a4364fe81bd"},"datetime":"31/10/1981 18:00","city":"weed","state":"ca","country":"us","shape":"disk","duration_seconds":600,"duration_hours_min":"10 minutes","comments":"10/31/1981 Saucer Shaped UFO hovering between the moutain Mt. Shasta and the city of Mt. Shasta California","date posted":"05/08/2009","latitude":41.4227778,"longitude":-122.385}
{"_id":{"$oid":"658c638218dd9a4364fe820a"},"datetime":"31/10/2001 20:35","city":"atlantic","state":"ia","country":"us","shape":"sphere","duration_seconds":1.5,"duration_hours_min":"1-1.5 seconds","comments":"A glowing blue ball quickly passed in and out of low hazy clouds right above me.","date posted":"20/11/2001","latitude":41.4036111,"longitude":-95.0136111}
{"_id":{"$oid":"658c638218dd9a4364fe8228"},"datetime":"31/10/2003 22:00","city":"wakefield","state":"ri","country":"us","shape":"triangle","duration_seconds":120,"duration_hours_min":"2 minutes","comments":"Large triangular object flying fairly low over Route 1 in wakefield Rhode Island on Halloween.  4 large white lights.","date posted":"08/11/2003","latitude":41.4372222,"longitude":-71.5019444}
{"_id":{"$oid":"658c638218dd9a4364fe8242"},"datetime":"31/10/2004 19:50","city":"frankfort","state":"il","country":"us","shape":"light","duration_seconds":1500,"duration_hours_min":"25 minutes","comments":"3 red lights in formation traveling southeast slowly and faded out one by one.","date posted":"02/11/2004","latitude":41.4958333,"longitude":-87.8486111}
{"_id":{"$oid":"658c638218dd9a4364fe8244"},"datetime":"31/10/2004 19:56","city":"matteson","state":"il","country":"us","shape":"NULL","duration_seconds":960,"duration_hours_min":"16 minutes","comments":"3 very bright red lights.","date posted":"02/11/2004","latitude":41.5038889,"longitude":-87.7130556}
{"_id":{"$oid":"658c638218dd9a4364fe825e"},"datetime":"31/10/2004 20:06","city":"manhattan","state":"il","country":"us","shape":"light","duration_seconds":60,"duration_hours_min":"1 minute","comments":"Red Lights seen from 2 different locations at same time while on phone with family member.","date posted":"02/11/2004","latitude":41.4225,"longitude":-87.9858333}
{"_id":{"$oid":"658c638218dd9a4364fe8263"},"datetime":"31/10/2004 20:15","city":"mokena","state":"il","country":"us","shape":"light","duration_seconds":900,"duration_hours_min":"15 min","comments":"3 red blinking lights in triangle formation and barely moving.moving into a single file line and than disapearing one by one.in","date posted":"02/11/2004","latitude":41.5261111,"longitude":-87.8891667}
{"_id":{"$oid":"658c638218dd9a4364fe82c6"},"datetime":"31/10/2008 18:53","city":"moline","state":"il","country":"us","shape":"circle","duration_seconds":240,"duration_hours_min":"4 min","comments":"Two seperate orbs pass slowly over my house.","date posted":"10/01/2009","latitude":41.5066667,"longitude":-90.515}
{"_id":{"$oid":"658c638218dd9a4364fe82c7"},"datetime":"31/10/2008 19:00","city":"wakefield","state":"ri","country":"us","shape":"flash","duration_seconds":1,"duration_hours_min":"1 second","comments":"Bright&#44 white flash","date posted":"10/01/2009","latitude":41.4372222,"longitude":-71.5019444}
{"_id":{"$oid":"658c638218dd9a4364fe82ff"},"datetime":"31/10/2011 19:00","city":"parma","state":"oh","country":"us","shape":"light","duration_seconds":60,"duration_hours_min":"1 min","comments":"Halloween lights over Parma Ohio","date posted":"12/12/2011","latitude":41.4047222,"longitude":-81.7230556}
{"_id":{"$oid":"658c638218dd9a4364fe837a"},"datetime":"03/10/2004 19:05","city":"cleveland","state":"oh","country":"us","shape":"circle","duration_seconds":30,"duration_hours_min":"30sec.","comments":"Many fighter jets flying towards UFO","date posted":"27/10/2004","latitude":41.4994444,"longitude":-81.6955556}
{"_id":{"$oid":"658c638218dd9a4364fe83f6"},"datetime":"03/10/2013 21:00","city":"rocky river","state":"oh","country":"us","shape":"fireball","duration_seconds":15,"duration_hours_min":"15 seconds","comments":"Fireball seen across Cleveland sky.","date posted":"14/10/2013","latitude":41.4755556,"longitude":-81.8394444}
{"_id":{"$oid":"658c638218dd9a4364fe843c"},"datetime":"04/10/2003 21:30","city":"la moille","state":"il","country":"us","shape":"changing","duration_seconds":2700,"duration_hours_min":"45 min","comments":"My wife used to be a  skeptic&#44 now she doesnt know what to say but that it was the most  amazing thing she`s ever seen","date posted":"07/10/2003","latitude":41.5316667,"longitude":-89.2797222}
{"_id":{"$oid":"658c638218dd9a4364fe853c"},"datetime":"05/10/2010 19:00","city":"de soto","state":"ia","country":"us","shape":"light","duration_seconds":3600,"duration_hours_min":"1 hour","comments":"5 amazingly bright  light objects in  bright redish/orange  October sunset. in  IOWA.","date posted":"21/11/2010","latitude":41.5316667,"longitude":-94.0094444}
{"_id":{"$oid":"658c638218dd9a4364fe85b3"},"datetime":"06/10/2001 22:00","city":"park forest","state":"il","country":"us","shape":"triangle","duration_seconds":15,"duration_hours_min":"15 seconds","comments":"THE AIRCRAFT WAS SHAPE LIKE A TRIANGLE WITH CIRCLE LIGHTS IN EACH CORNER TER WITH A LIGHT IN THE MIDDLE A REDDISH ORANGE LIGHT WAS BLIN","date posted":"12/10/2001","latitude":41.4913889,"longitude":-87.6744444}
{"_id":{"$oid":"658c638218dd9a4364fe85de"},"datetime":"06/10/2005 11:00","city":"park forest","state":"il","country":"us","shape":"oval","duration_seconds":300,"duration_hours_min":"5 mins","comments":"I saw 3 round strange looking objects in the sky","date posted":"11/10/2005","latitude":41.4913889,"longitude":-87.6744444}
{"_id":{"$oid":"658c638218dd9a4364fe85fe"},"datetime":"06/10/2008 20:00","city":"chagrin falls","state":"oh","country":"us","shape":"triangle","duration_seconds":600,"duration_hours_min":"10 minutes","comments":"It was to long and going much to slow to be a plane. It was huge&#44 I couldn&#39t believe what i has seen.","date posted":"31/10/2008","latitude":41.4361111,"longitude":-81.3866667}
{"_id":{"$oid":"658c638218dd9a4364fe8693"},"datetime":"07/10/2003 18:00","city":"meriden","state":"ct","country":"us","shape":"disk","duration_seconds":60,"duration_hours_min":"1 min","comments":"Bright reflection off an object but not like an airplane it moved from the left of the sky to the right and then to the left again","date posted":"31/10/2003","latitude":41.5380556,"longitude":-72.8075}
{"_id":{"$oid":"658c638218dd9a4364fe86e9"},"datetime":"07/10/2011 23:36","city":"cleveland","state":"oh","country":"us","shape":"fireball","duration_seconds":300,"duration_hours_min":"5 minutes?","comments":"Glowing fireball object traveling in Cleveland sky NW towards the Lake?","date posted":"19/10/2011","latitude":41.4994444,"longitude":-81.6955556}
{"_id":{"$oid":"658c638218dd9a4364fe8767"},"datetime":"08/10/2008 18:45","city":"wakefield","state":"ri","country":"us","shape":"formation","duration_seconds":180,"duration_hours_min":"3 min","comments":"2 sets of 5 or 6 red tumbling lights move steadily across southern sky.","date posted":"10/01/2009","latitude":41.4372222,"longitude":-71.5019444}
{"_id":{"$oid":"658c638218dd9a4364fe8780"},"datetime":"08/10/2010 05:30","city":"tunkhannock","state":"pa","country":"us","shape":"unknown","duration_seconds":600,"duration_hours_min":"10 minutes","comments":"3 star looking objects running in straight line formation north -north west then the leader turned left","date posted":"21/11/2010","latitude":41.5386111,"longitude":-75.9469444}
{"_id":{"$oid":"658c638218dd9a4364fe878b"},"datetime":"08/10/2010 21:05","city":"cleveland heights","state":"oh","country":"us","shape":"circle","duration_seconds":30,"duration_hours_min":"30 seconds","comments":"Friend and I were standing outside in cleveland heights. Saw a round orange-like orb moving from South to north; difficult to estimate","date posted":"21/11/2010","latitude":41.52,"longitude":-81.5563889}
{"_id":{"$oid":"658c638218dd9a4364fe8857"},"datetime":"09/10/2010 21:15","city":"port clinton","state":"oh","country":"us","shape":"fireball","duration_seconds":240,"duration_hours_min":"4 min.","comments":"Glowing ball sighted over the Catawba Point waters of Lake Erie","date posted":"21/11/2010","latitude":41.5119444,"longitude":-82.9377778}
{"_id":{"$oid":"658c638218dd9a4364fe88b7"},"datetime":"10/01/1995 21:00","city":"cleveland heights","state":"oh","country":"us","shape":"sphere","duration_seconds":20,"duration_hours_min":"20 seconds","comments":"Glowing orb changes color and heads straight into Lake Erie.","date posted":"26/11/2003","latitude":41.52,"longitude":-81.5563889}
{"_id":{"$oid":"658c638218dd9a4364fe88da"},"datetime":"10/01/2003 18:30","city":"woodbury","state":"ct","country":"us","shape":"oval","duration_seconds":1800,"duration_hours_min":"30 minutes","comments":"Oval orange glowing object hovers over Three Rivers Park&#44 shoots laser-beam to ground. Not a balloon&#33","date posted":"21/03/2003","latitude":41.5444444,"longitude":-73.2094444}
{"_id":{"$oid":"658c638218dd9a4364fe88f2"},"datetime":"10/01/2004 19:15","city":"naugatuck","state":"ct","country":"us","shape":"light","duration_seconds":900,"duration_hours_min":"about 15 min","comments":"Erratic-moving amber light in sky","date posted":"17/01/2004","latitude":41.4858333,"longitude":-73.0511111}
{"_id":{"$oid":"658c638218dd9a4364fe89eb"},"datetime":"10/11/2005 19:15","city":"kingstown","state":"ri","country":"NULL","shape":"light","duration_seconds":5,"duration_hours_min":"5 sec","comments":"a large light overhead going north&#445 times the size of a planes&#39light&#44 disapearing behind clou","date posted":"16/12/2005","latitude":41.485711,"longitude":-71.563662}
{"_id":{"$oid":"658c638218dd9a4364fe8a11"},"datetime":"10/11/2010 18:00","city":"crete","state":"il","country":"us","shape":"formation","duration_seconds":900,"duration_hours_min":"15 minutes","comments":"4 orange lights in formation","date posted":"21/11/2010","latitude":41.4444444,"longitude":-87.6313889}
{"_id":{"$oid":"658c638218dd9a4364fe8a13"},"datetime":"10/11/2010 19:40","city":"montville","state":"ct","country":"NULL","shape":"disk","duration_seconds":1200,"duration_hours_min":"20 mins","comments":"a huge disk shaped object that covered half the sky","date posted":"21/11/2010","latitude":41.463992,"longitude":-72.155619}
{"_id":{"$oid":"658c638218dd9a4364fe8a9c"},"datetime":"11/11/2001 20:04","city":"carmel","state":"ny","country":"us","shape":"triangle","duration_seconds":120,"duration_hours_min":"2 mins","comments":"2 Triangular shaped craft in Putnam County","date posted":"20/11/2001","latitude":41.43,"longitude":-73.6805556}
{"_id":{"$oid":"658c638218dd9a4364fe8afa"},"datetime":"11/11/2010 19:20","city":"uncasville","state":"ct","country":"us","shape":"light","duration_seconds":45,"duration_hours_min":"45 sec.","comments":"V shaped light formation over Montville Ct.","date posted":"21/11/2010","latitude":41.4344444,"longitude":-72.1102778}
{"_id":{"$oid":"658c638218dd9a4364fe8b55"},"datetime":"01/11/1974 21:00","city":"oil city","state":"pa","country":"us","shape":"unknown","duration_seconds":7200,"duration_hours_min":"1-2 hours","comments":"Bright lights in the sky seperated by several miles moving in odd geometric directions--changing course instantly","date posted":"16/04/2005","latitude":41.4338889,"longitude":-79.7066667}
{"_id":{"$oid":"658c638218dd9a4364fe8b5f"},"datetime":"01/11/1979 16:30","city":"meriden","state":"ct","country":"us","shape":"light","duration_seconds":120,"duration_hours_min":"2mins","comments":"I was 14 years old and lived at Sidehill Rd.I had just finished supper and decided to go up the street to my friends house at the top o","date posted":"02/09/2005","latitude":41.5380556,"longitude":-72.8075}
{"_id":{"$oid":"658c638218dd9a4364fe8b70"},"datetime":"01/11/1974 20:00","city":"davenport","state":"ia","country":"us","shape":"light","duration_seconds":600,"duration_hours_min":"10 minutes","comments":"On this particular clear sky evening in rural Iowa. I was leaving our farm and goin on a date in town. I was 17 at the time and was goi","date posted":"24/09/2003","latitude":41.5236111,"longitude":-90.5775}
{"_id":{"$oid":"658c638218dd9a4364fe8c5f"},"datetime":"01/11/2005 20:00","city":"clarks summit","state":"pa","country":"us","shape":"other","duration_seconds":20,"duration_hours_min":"20 secs","comments":"white streaks following one another","date posted":"08/11/2005","latitude":41.4886111,"longitude":-75.7088889}
{"_id":{"$oid":"658c638218dd9a4364fe8c62"},"datetime":"01/11/2005 23:00","city":"jamestown","state":"ri","country":"us","shape":"light","duration_seconds":180,"duration_hours_min":"2-3 minutes","comments":"Lights in the november sky","date posted":"08/11/2005","latitude":41.4969444,"longitude":-71.3677778}
{"_id":{"$oid":"658c638218dd9a4364fe8cbf"},"datetime":"01/11/2009 21:00","city":"merrillville","state":"in","country":"us","shape":"disk","duration_seconds":600,"duration_hours_min":"10 minutes","comments":"Five fireball objects which were being escorted by military helicopters. The picture I took showed five disc shaped objects","date posted":"12/12/2009","latitude":41.4827778,"longitude":-87.3327778}
{"_id":{"$oid":"658c638218dd9a4364fe8cf6"},"datetime":"01/11/2011 22:30","city":"washingtonville","state":"ny","country":"us","shape":"triangle","duration_seconds":300,"duration_hours_min":"5 minutes","comments":"((HOAX))  100 yard long giant black silent triangle 150FT hovering above me and friend silent.","date posted":"23/12/2013","latitude":41.4277778,"longitude":-74.1663889}
{"_id":{"$oid":"658c638218dd9a4364fe8d06"},"datetime":"11/01/2012 17:30","city":"wallingford","state":"ct","country":"us","shape":"light","duration_seconds":1800,"duration_hours_min":"30 mins","comments":"Teal ball of light hovers for nearly 30 mins then lowers below tree line in Yalesville&#44 CT","date posted":"24/01/2012","latitude":41.4569444,"longitude":-72.8236111}
{"_id":{"$oid":"658c638218dd9a4364fe8d14"},"datetime":"01/11/2012 20:00","city":"joliet","state":"il","country":"us","shape":"formation","duration_seconds":300,"duration_hours_min":"5 minutes","comments":"7 Orange-Red lights hovering over Joliet&#44 IL","date posted":"04/11/2012","latitude":41.525,"longitude":-88.0816667}
{"_id":{"$oid":"658c638218dd9a4364fe8dad"},"datetime":"12/11/2004 15:15","city":"cleveland","state":"oh","country":"us","shape":"circle","duration_seconds":20,"duration_hours_min":"20 seconds","comments":"Circle (Silver) perfect in shape&#44 flying at speeds at least 3X faster than a fighter jet","date posted":"03/12/2004","latitude":41.4994444,"longitude":-81.6955556}
{"_id":{"$oid":"658c638218dd9a4364fe8ddb"},"datetime":"12/11/2008 21:30","city":"wallingford","state":"ct","country":"us","shape":"fireball","duration_seconds":3,"duration_hours_min":"3 seconds","comments":"I saw a green object flash across the sky","date posted":"10/01/2009","latitude":41.4569444,"longitude":-72.8236111}
{"_id":{"$oid":"658c638218dd9a4364fe8e45"},"datetime":"13/11/1998 01:30","city":"maybrook","state":"ny","country":"us","shape":"NULL","duration_seconds":300,"duration_hours_min":"5 minutes","comments":"I have seen aliens in my home&#33","date posted":"05/08/2001","latitude":41.4838889,"longitude":-74.2180556}
{"_id":{"$oid":"658c638218dd9a4364fe8fad"},"datetime":"14/11/2010 21:00","city":"washingtonville","state":"ny","country":"us","shape":"unknown","duration_seconds":120,"duration_hours_min":"2 minutes","comments":"The lights&#44 that type of illumination on a plane or jet I have never seen before&#44 and ONLY 2 of them&#44 no others.","date posted":"21/11/2010","latitude":41.4277778,"longitude":-74.1663889}
{"_id":{"$oid":"658c638218dd9a4364fe8fb5"},"datetime":"14/11/2011 18:50","city":"green river","state":"wy","country":"us","shape":"triangle","duration_seconds":15,"duration_hours_min":"15 sec","comments":"I was in my back yard and loooked up  and saw 3 perfecct  lights  in  a fast direction to the north then two otheerr ligghts  vered of","date posted":"12/12/2011","latitude":41.5286111,"longitude":-109.4655556}
{"_id":{"$oid":"658c638218dd9a4364fe9012"},"datetime":"15/11/1977 01:00","city":"newburgh","state":"ny","country":"us","shape":"disk","duration_seconds":600,"duration_hours_min":"10 minutes","comments":"Stationary UFO in Newburgh Upstate New York 1975.  ((NUFORC Note:  Date corrected to November 15&#44 1977.  PD))","date posted":"08/10/2007","latitude":41.5033333,"longitude":-74.0108333}
{"_id":{"$oid":"658c638218dd9a4364fe9013"},"datetime":"15/11/1976 23:00","city":"bedford heights","state":"oh","country":"us","shape":"oval","duration_seconds":900,"duration_hours_min":"10-15 min","comments":"LIGHT BLUE OBJECT LITE UP WAS SEEN DOING SUDDEN STARTS AND STOPS FREQUENT DIRCTION CHANGES FOR 10-15 MIN","date posted":"25/07/2004","latitude":41.4169444,"longitude":-81.5275}
{"_id":{"$oid":"658c638218dd9a4364fe9045"},"datetime":"15/11/1993 12:00","city":"rome city","state":"in","country":"us","shape":"egg","duration_seconds":180,"duration_hours_min":"3 minutes","comments":"Two eggshaped objects hovered in the sky then speed away.","date posted":"28/08/2003","latitude":41.4961111,"longitude":-85.3766667}
{"_id":{"$oid":"658c638218dd9a4364fe90ac"},"datetime":"15/11/2002 22:00","city":"sheffield lake","state":"oh","country":"us","shape":"circle","duration_seconds":180,"duration_hours_min":"3 min","comments":"A BRIGHT LIGHT WAS MOVING JUST ABOVE THE CLOUDS VERY SLOWLY FROM NORTH TO SOUTH.","date posted":"19/12/2003","latitude":41.4875,"longitude":-82.1016667}
{"_id":{"$oid":"658c638218dd9a4364fe9104"},"datetime":"15/11/2006 23:00","city":"lorain","state":"oh","country":"us","shape":"unknown","duration_seconds":1800,"duration_hours_min":"30 minutes","comments":"I saw different colored lights in the sky southeast of me","date posted":"01/02/2007","latitude":41.4527778,"longitude":-82.1825}
{"_id":{"$oid":"658c638218dd9a4364fe9108"},"datetime":"15/11/2007 03:00","city":"scranton/dunmore","state":"pa","country":"NULL","shape":"disk","duration_seconds":2,"duration_hours_min":"1-2 seconds","comments":"Extremly large and bright blue disc shaped object soared through sky leaving trail of light in Northeast Pennsylvania.","date posted":"04/03/2008","latitude":41.44012,"longitude":-75.620837}
{"_id":{"$oid":"658c638218dd9a4364fe9144"},"datetime":"15/11/2011 17:30","city":"parma","state":"oh","country":"us","shape":"cigar","duration_seconds":1800,"duration_hours_min":"15-30 min","comments":"Pipe coming thru the clouds out of the atmosphere","date posted":"12/12/2011","latitude":41.4047222,"longitude":-81.7230556}
{"_id":{"$oid":"658c638218dd9a4364fe91a4"},"datetime":"16/11/1999 02:00","city":"griffith","state":"in","country":"us","shape":"flash","duration_seconds":120,"duration_hours_min":"1-2 minutes","comments":"In the early morning&#44 I saw very bright lights shinning into my window.  The flashes of light were so bright that I thought something b","date posted":"22/01/2000","latitude":41.5283333,"longitude":-87.4236111}
{"_id":{"$oid":"658c638218dd9a4364fe91bc"},"datetime":"16/11/1999 18:04","city":"norwalk (sml town just sw of des moines)","state":"ia","country":"us","shape":"fireball","duration_seconds":8,"duration_hours_min":"6-8 seconds","comments":"this was a blue-green fireball seen by myself&#44 my husband and our young son.  it was moving from the south to the northeast.  my husban","date posted":"17/11/1999","latitude":41.4755556,"longitude":-93.6786111}
{"_id":{"$oid":"658c638218dd9a4364fe91eb"},"datetime":"16/11/1999 19:00","city":"cleveland","state":"oh","country":"us","shape":"light","duration_seconds":300,"duration_hours_min":"5min.","comments":"It was rock shape fire balls moving very slowly Over the raped station it was coming from east to west.","date posted":"17/11/1999","latitude":41.4994444,"longitude":-81.6955556}
{"_id":{"$oid":"658c638218dd9a4364fe9210"},"datetime":"16/11/1999 19:05","city":"cleveland","state":"oh","country":"us","shape":"fireball","duration_seconds":25,"duration_hours_min":"25 sec.","comments":"Objects split over the city.  Originally looked like a &#39firework&quot; passed east to west as i was looking north.","date posted":"17/11/1999","latitude":41.4994444,"longitude":-81.6955556}
{"_id":{"$oid":"658c638218dd9a4364fe921f"},"datetime":"16/11/1999 19:06","city":"parma","state":"oh","country":"us","shape":"circle","duration_seconds":240,"duration_hours_min":"3to4min.","comments":"saw 6 to 7 white round obects with green glow going&#44.. across the sky towrds the East&#44 not in a fast pace&#44 but slow...the objects had t","date posted":"17/11/1999","latitude":41.4047222,"longitude":-81.7230556}
{"_id":{"$oid":"658c638218dd9a4364fe9228"},"datetime":"16/11/1999 19:10","city":"cleveland","state":"oh","country":"us","shape":"disk","duration_seconds":5,"duration_hours_min":"5 seconds","comments":"Dear Sirs&#44 My name is ((name deleted)) 36yr old biomedical engineering tech for a local dialysis center. I observed on date reported","date posted":"23/11/1999","latitude":41.4994444,"longitude":-81.6955556}
{"_id":{"$oid":"658c638218dd9a4364fe923c"},"datetime":"16/11/1999 19:15","city":"cleveland","state":"oh","country":"us","shape":"egg","duration_seconds":3,"duration_hours_min":"2-3 sec","comments":"I was reading the reports from last year of the four fast moving objects Nov.&#3999. I also reported it to you. And their was a note that","date posted":"02/12/2000","latitude":41.4994444,"longitude":-81.6955556}
{"_id":{"$oid":"658c638218dd9a4364fe9268"},"datetime":"16/11/2003 06:30","city":"santa bonifacio (corsica)","state":"NULL","country":"NULL","shape":"disk","duration_seconds":600,"duration_hours_min":"10 minutes approx","comments":"Moon  colored disk objects sighted from the second floor of Le Royal Hotel at 6:30 AM Nov. 16&#44 2003","date posted":"19/12/2003","latitude":41.481793,"longitude":9.06108}
{"_id":{"$oid":"658c638218dd9a4364fe927f"},"datetime":"16/11/2004 21:00","city":"newport","state":"ri","country":"us","shape":"triangle","duration_seconds":240,"duration_hours_min":"4 min","comments":"11-16-04 On this night both the anniversary of my fathers death and the birth of my grandfather I had an intense UFO experience. While","date posted":"30/10/2006","latitude":41.49,"longitude":-71.3133333}
{"_id":{"$oid":"658c638218dd9a4364fe92b3"},"datetime":"16/11/2009 19:00","city":"monee","state":"il","country":"us","shape":"light","duration_seconds":600,"duration_hours_min":"5-10 minutes","comments":"incredibly bright white solid light that hovered for 5-10 minutes then disappeared","date posted":"12/12/2009","latitude":41.42,"longitude":-87.7416667}
{"_id":{"$oid":"658c638218dd9a4364fe92e0"},"datetime":"16/11/2012 18:14","city":"greenville","state":"pa","country":"us","shape":"unknown","duration_seconds":300,"duration_hours_min":"<5 minutes","comments":"Red/orange lights seen for about 4 minutes in Western Pennsylvania","date posted":"19/11/2012","latitude":41.4044444,"longitude":-80.3913889}
{"_id":{"$oid":"658c638218dd9a4364fe92f9"},"datetime":"16/11/2013 18:00","city":"meriden","state":"ct","country":"us","shape":"fireball","duration_seconds":1800,"duration_hours_min":"30 minutes","comments":"I was driving up east Main Street to dunkin donuts when to my left I saw like 8 balls of orange/red in the sky. I went to dd and on my","date posted":"20/11/2013","latitude":41.5380556,"longitude":-72.8075}
{"_id":{"$oid":"658c638218dd9a4364fe92fb"},"datetime":"16/11/2013 18:30","city":"jamestown","state":"ri","country":"us","shape":"fireball","duration_seconds":480,"duration_hours_min":"8 minutes","comments":"When outside with our dog around 6:30 pm on Sat.&#44 Nov. 16th&#44 I spotted a bright white orange light pulsating somewhat coming above the","date posted":"20/11/2013","latitude":41.4969444,"longitude":-71.3677778}
{"_id":{"$oid":"658c638218dd9a4364fe9335"},"datetime":"17/11/1998 05:00","city":"davenport","state":"ia","country":"us","shape":"triangle","duration_seconds":240,"duration_hours_min":"4 min","comments":"Triangular shaped noiseless craft flew over head at approx 150 feet heading south by south west from my location.","date posted":"19/11/1998","latitude":41.5236111,"longitude":-90.5775}
{"_id":{"$oid":"658c638218dd9a4364fe933d"},"datetime":"17/11/1998 21:00","city":"cleveland","state":"oh","country":"us","shape":"egg","duration_seconds":120,"duration_hours_min":"2 minutes","comments":"I have utmost respect for Peter Davenport and his attempts to categorize and document UFO anomalies. I am also dumbfounded that my","date posted":"15/09/2005","latitude":41.4994444,"longitude":-81.6955556}
{"_id":{"$oid":"658c638218dd9a4364fe9344"},"datetime":"17/11/1999 03:00","city":"sandusky","state":"oh","country":"us","shape":"sphere","duration_seconds":900,"duration_hours_min":"15 min.","comments":"About 20 silver spheres were seen circling a jumbo jet in formation. They were extremely fast and formatted into a V shape at one point","date posted":"17/11/1999","latitude":41.4488889,"longitude":-82.7080556}
{"_id":{"$oid":"658c638218dd9a4364fe937c"},"datetime":"17/11/2005 21:30","city":"perry","state":"ut","country":"us","shape":"other","duration_seconds":60,"duration_hours_min":"1 minute","comments":"300 hundred above me an arrowhead oblonged cone shape object  flew slow above me. Anyone else?","date posted":"16/12/2005","latitude":41.465,"longitude":-112.0316667}
{"_id":{"$oid":"658c638218dd9a4364fe938f"},"datetime":"17/11/2007 20:15","city":"monee","state":"il","country":"us","shape":"unknown","duration_seconds":150,"duration_hours_min":"2.5 min","comments":"Two bright objects just south of Chicago never moving&#44 just fad away.","date posted":"28/11/2007","latitude":41.42,"longitude":-87.7416667}
{"_id":{"$oid":"658c638218dd9a4364fe93ee"},"datetime":"17/11/2011 22:00","city":"monee","state":"il","country":"us","shape":"triangle","duration_seconds":20,"duration_hours_min":"20 seconds","comments":"Dark triangular wing in night sky","date posted":"12/12/2011","latitude":41.42,"longitude":-87.7416667}
